CHANGES.rst
MANIFEST.in
README.rst
setup.cfg
setup.py
docs/Makefile
docs/make.bat
docs/_images/setup_select_add_on.png
docs/source/conf.py
docs/source/configuration.rst
docs/source/index.rst
docs/source/_static/empty
docs/source/_static/logo.png
docs/source/_templates/empty
src/ps/__init__.py
src/ps.plone.fotorama.egg-info/PKG-INFO
src/ps.plone.fotorama.egg-info/SOURCES.txt
src/ps.plone.fotorama.egg-info/dependency_links.txt
src/ps.plone.fotorama.egg-info/entry_points.txt
src/ps.plone.fotorama.egg-info/namespace_packages.txt
src/ps.plone.fotorama.egg-info/not-zip-safe
src/ps.plone.fotorama.egg-info/requires.txt
src/ps.plone.fotorama.egg-info/top_level.txt
src/ps/plone/__init__.py
src/ps/plone/fotorama/__init__.py
src/ps/plone/fotorama/config.py
src/ps/plone/fotorama/configure.zcml
src/ps/plone/fotorama/profiles.zcml
src/ps/plone/fotorama/setuphandlers.py
src/ps/plone/fotorama/testing.py
src/ps/plone/fotorama/browser/__init__.py
src/ps/plone/fotorama/browser/configure.zcml
src/ps/plone/fotorama/browser/interfaces.py
src/ps/plone/fotorama/browser/static/fotorama.css
src/ps/plone/fotorama/browser/static/fotorama.js
src/ps/plone/fotorama/browser/static/fotorama.png
src/ps/plone/fotorama/browser/static/fotorama@2x.png
src/ps/plone/fotorama/locales/manual.pot
src/ps/plone/fotorama/locales/plone.pot
src/ps/plone/fotorama/locales/ps.plone.fotorama.pot
src/ps/plone/fotorama/profiles/base/metadata.xml
src/ps/plone/fotorama/profiles/plone4/browserlayer.xml
src/ps/plone/fotorama/profiles/plone4/cssregistry.xml
src/ps/plone/fotorama/profiles/plone4/jsregistry.xml
src/ps/plone/fotorama/profiles/plone4/metadata.xml
src/ps/plone/fotorama/profiles/plone5/browserlayer.xml
src/ps/plone/fotorama/profiles/plone5/metadata.xml
src/ps/plone/fotorama/profiles/plone5/registry.xml
src/ps/plone/fotorama/profiles/uninstall-base/browserlayer.xml
src/ps/plone/fotorama/profiles/uninstall-plone4/metadata.xml
src/ps/plone/fotorama/profiles/uninstall-plone5/metadata.xml
src/ps/plone/fotorama/tests/__init__.py
src/ps/plone/fotorama/tests/test_robot.py
src/ps/plone/fotorama/tests/test_setup.py
src/ps/plone/fotorama/tests/robot/__init__.py
src/ps/plone/fotorama/tests/robot/keywords.robot
src/ps/plone/fotorama/tests/robot/test_setup.robot