Metadata-Version: 1.1
Name: ps.plone.fotorama
Version: 4.6.4.3
Summary: Fotorama slideshow for Plone.
Home-page: https://github.com/propertyshelf/ps.plone.fotorama
Author: Propertyshelf, Inc.
Author-email: development@propertyshelf.com
License: GPL
Download-URL: http://pypi.python.org/pypi/ps.plone.fotorama
Keywords: plone zope fotorama slideshow
Platform: UNKNOWN
Classifier: Development Status :: 4 - Beta
Classifier: Environment :: Web Environment
Classifier: Framework :: Plone
Classifier: Framework :: Plone :: 4.2
Classifier: Framework :: Plone :: 4.3
Classifier: Framework :: Plone :: 5.0
Classifier: Framework :: Plone :: 5.1
Classifier: Intended Audience :: Developers
Classifier: License :: OSI Approved :: GNU General Public License v2 (GPLv2)
Classifier: Programming Language :: Python
Classifier: Programming Language :: Python :: 2.6
Classifier: Programming Language :: Python :: 2.7
